{
  "$otSharedSchema": "#/pipette/schemas/2/pipettePropertiesSchema.json",
  "displayName": "P1000 96 Channel GEN3",
  "model": "p1000",
  "displayCategory": "GEN3",
  "pickUpTipConfigurations": {
    "current": 1.5,
    "presses": 0.0,
    "speed": 5.5,
    "increment": 0.0,
    "distance": 19.0
  },
  "dropTipConfigurations": { "current": 1.5, "speed": 5.5, "distance": 26.5 },
  "plungerMotorConfigurations": { "idle": 0.3, "run": 2.0 },
  "plungerPositionsConfigurations": {
    "top": 0,
    "bottom": 66,
    "blowout": 71,
    "drop": 80
  },
  "availableSensors": {
    "sensors": ["pressure", "capacitive", "environment"],
    "pressure": { "count": 2 },
    "capacitive": { "count": 2 },
    "environment": { "count": 1 }
  },
  "partialTipConfigurations": {
    "partialTipSupported": true,
    "availableConfigurations": [1, 8, 12, 96]
  },
  "backCompatNames": [],
  "channels": 96,
  "shaftDiameter": 9.0,
  "shaftULperMM": 63.617,
  "backlashDistance": 0.3
}
