{
  "metadata": {
    "name": "tiprack-1000ul-H",
    "format": "96-standard",
    "deprecated": true
  },
  "ordering": [
    ["A1", "B1", "C1", "D1"],
    ["A2", "B2", "C2", "D2"],
    ["A3", "B3", "C3", "D3"],
    ["A4", "B4", "C4", "D4"],
    ["A5", "B5", "C5", "D5"],
    ["A6", "B6", "C6", "D6"],
    ["A7", "B7", "C7", "D7"],
    ["A8", "B8", "C8", "D8"],
    ["A9", "B9", "C9", "D9"],
    ["A10", "B10", "C10", "D10"],
    ["A11", "B11", "C11", "D11"],
    ["A12", "B12", "C12", "D12"]
  ],
  "wells": {
    "A1": {
      "depth": 85,
      "diameter": 6.4,
      "height": 85,
      "length": 6.4,
      "width": 6.4,
      "x": 11.14,
      "y": 35.04,
      "z": 0
    },
    "A10": {
      "depth": 85,
      "diameter": 6.4,
      "height": 85,
      "length": 6.4,
      "width": 6.4,
      "x": 92.14,
      "y": 35.04,
      "z": 0
    },
    "A11": {
      "depth": 85,
      "diameter": 6.4,
      "height": 85,
      "length": 6.4,
      "width": 6.4,
      "x": 101.14,
      "y": 35.04,
      "z": 0
    },
    "A12": {
      "depth": 85,
      "diameter": 6.4,
      "height": 85,
      "length": 6.4,
      "width": 6.4,
      "x": 110.14,
      "y": 35.04,
      "z": 0
    },
    "A2": {
      "depth": 85,
      "diameter": 6.4,
      "height": 85,
      "length": 6.4,
      "width": 6.4,
      "x": 20.14,
      "y": 35.04,
      "z": 0
    },
    "A3": {
      "depth": 85,
      "diameter": 6.4,
      "height": 85,
      "length": 6.4,
      "width": 6.4,
      "x": 29.14,
      "y": 35.04,
      "z": 0
    },
    "A4": {
      "depth": 85,
      "diameter": 6.4,
      "height": 85,
      "length": 6.4,
      "width": 6.4,
      "x": 38.14,
      "y": 35.04,
      "z": 0
    },
    "A5": {
      "depth": 85,
      "diameter": 6.4,
      "height": 85,
      "length": 6.4,
      "width": 6.4,
      "x": 47.14,
      "y": 35.04,
      "z": 0
    },
    "A6": {
      "depth": 85,
      "diameter": 6.4,
      "height": 85,
      "length": 6.4,
      "width": 6.4,
      "x": 56.14,
      "y": 35.04,
      "z": 0
    },
    "A7": {
      "depth": 85,
      "diameter": 6.4,
      "height": 85,
      "length": 6.4,
      "width": 6.4,
      "x": 65.14,
      "y": 35.04,
      "z": 0
    },
    "A8": {
      "depth": 85,
      "diameter": 6.4,
      "height": 85,
      "length": 6.4,
      "width": 6.4,
      "x": 74.14,
      "y": 35.04,
      "z": 0
    },
    "A9": {
      "depth": 85,
      "diameter": 6.4,
      "height": 85,
      "length": 6.4,
      "width": 6.4,
      "x": 83.14,
      "y": 35.04,
      "z": 0
    },
    "B1": {
      "depth": 85,
      "diameter": 6.4,
      "height": 85,
      "length": 6.4,
      "width": 6.4,
      "x": 11.14,
      "y": 26.04,
      "z": 0
    },
    "B10": {
      "depth": 85,
      "diameter": 6.4,
      "height": 85,
      "length": 6.4,
      "width": 6.4,
      "x": 92.14,
      "y": 26.04,
      "z": 0
    },
    "B11": {
      "depth": 85,
      "diameter": 6.4,
      "height": 85,
      "length": 6.4,
      "width": 6.4,
      "x": 101.14,
      "y": 26.04,
      "z": 0
    },
    "B12": {
      "depth": 85,
      "diameter": 6.4,
      "height": 85,
      "length": 6.4,
      "width": 6.4,
      "x": 110.14,
      "y": 26.04,
      "z": 0
    },
    "B2": {
      "depth": 85,
      "diameter": 6.4,
      "height": 85,
      "length": 6.4,
      "width": 6.4,
      "x": 20.14,
      "y": 26.04,
      "z": 0
    },
    "B3": {
      "depth": 85,
      "diameter": 6.4,
      "height": 85,
      "length": 6.4,
      "width": 6.4,
      "x": 29.14,
      "y": 26.04,
      "z": 0
    },
    "B4": {
      "depth": 85,
      "diameter": 6.4,
      "height": 85,
      "length": 6.4,
      "width": 6.4,
      "x": 38.14,
      "y": 26.04,
      "z": 0
    },
    "B5": {
      "depth": 85,
      "diameter": 6.4,
      "height": 85,
      "length": 6.4,
      "width": 6.4,
      "x": 47.14,
      "y": 26.04,
      "z": 0
    },
    "B6": {
      "depth": 85,
      "diameter": 6.4,
      "height": 85,
      "length": 6.4,
      "width": 6.4,
      "x": 56.14,
      "y": 26.04,
      "z": 0
    },
    "B7": {
      "depth": 85,
      "diameter": 6.4,
      "height": 85,
      "length": 6.4,
      "width": 6.4,
      "x": 65.14,
      "y": 26.04,
      "z": 0
    },
    "B8": {
      "depth": 85,
      "diameter": 6.4,
      "height": 85,
      "length": 6.4,
      "width": 6.4,
      "x": 74.14,
      "y": 26.04,
      "z": 0
    },
    "B9": {
      "depth": 85,
      "diameter": 6.4,
      "height": 85,
      "length": 6.4,
      "width": 6.4,
      "x": 83.14,
      "y": 26.04,
      "z": 0
    },
    "C1": {
      "depth": 85,
      "diameter": 6.4,
      "height": 85,
      "length": 6.4,
      "width": 6.4,
      "x": 11.14,
      "y": 17.04,
      "z": 0
    },
    "C10": {
      "depth": 85,
      "diameter": 6.4,
      "height": 85,
      "length": 6.4,
      "width": 6.4,
      "x": 92.14,
      "y": 17.04,
      "z": 0
    },
    "C11": {
      "depth": 85,
      "diameter": 6.4,
      "height": 85,
      "length": 6.4,
      "width": 6.4,
      "x": 101.14,
      "y": 17.04,
      "z": 0
    },
    "C12": {
      "depth": 85,
      "diameter": 6.4,
      "height": 85,
      "length": 6.4,
      "width": 6.4,
      "x": 110.14,
      "y": 17.04,
      "z": 0
    },
    "C2": {
      "depth": 85,
      "diameter": 6.4,
      "height": 85,
      "length": 6.4,
      "width": 6.4,
      "x": 20.14,
      "y": 17.04,
      "z": 0
    },
    "C3": {
      "depth": 85,
      "diameter": 6.4,
      "height": 85,
      "length": 6.4,
      "width": 6.4,
      "x": 29.14,
      "y": 17.04,
      "z": 0
    },
    "C4": {
      "depth": 85,
      "diameter": 6.4,
      "height": 85,
      "length": 6.4,
      "width": 6.4,
      "x": 38.14,
      "y": 17.04,
      "z": 0
    },
    "C5": {
      "depth": 85,
      "diameter": 6.4,
      "height": 85,
      "length": 6.4,
      "width": 6.4,
      "x": 47.14,
      "y": 17.04,
      "z": 0
    },
    "C6": {
      "depth": 85,
      "diameter": 6.4,
      "height": 85,
      "length": 6.4,
      "width": 6.4,
      "x": 56.14,
      "y": 17.04,
      "z": 0
    },
    "C7": {
      "depth": 85,
      "diameter": 6.4,
      "height": 85,
      "length": 6.4,
      "width": 6.4,
      "x": 65.14,
      "y": 17.04,
      "z": 0
    },
    "C8": {
      "depth": 85,
      "diameter": 6.4,
      "height": 85,
      "length": 6.4,
      "width": 6.4,
      "x": 74.14,
      "y": 17.04,
      "z": 0
    },
    "C9": {
      "depth": 85,
      "diameter": 6.4,
      "height": 85,
      "length": 6.4,
      "width": 6.4,
      "x": 83.14,
      "y": 17.04,
      "z": 0
    },
    "D1": {
      "depth": 85,
      "diameter": 6.4,
      "height": 85,
      "length": 6.4,
      "width": 6.4,
      "x": 11.14,
      "y": 8.04,
      "z": 0
    },
    "D10": {
      "depth": 85,
      "diameter": 6.4,
      "height": 85,
      "length": 6.4,
      "width": 6.4,
      "x": 92.14,
      "y": 8.04,
      "z": 0
    },
    "D11": {
      "depth": 85,
      "diameter": 6.4,
      "height": 85,
      "length": 6.4,
      "width": 6.4,
      "x": 101.14,
      "y": 8.04,
      "z": 0
    },
    "D12": {
      "depth": 85,
      "diameter": 6.4,
      "height": 85,
      "length": 6.4,
      "width": 6.4,
      "x": 110.14,
      "y": 8.04,
      "z": 0
    },
    "D2": {
      "depth": 85,
      "diameter": 6.4,
      "height": 85,
      "length": 6.4,
      "width": 6.4,
      "x": 20.14,
      "y": 8.04,
      "z": 0
    },
    "D3": {
      "depth": 85,
      "diameter": 6.4,
      "height": 85,
      "length": 6.4,
      "width": 6.4,
      "x": 29.14,
      "y": 8.04,
      "z": 0
    },
    "D4": {
      "depth": 85,
      "diameter": 6.4,
      "height": 85,
      "length": 6.4,
      "width": 6.4,
      "x": 38.14,
      "y": 8.04,
      "z": 0
    },
    "D5": {
      "depth": 85,
      "diameter": 6.4,
      "height": 85,
      "length": 6.4,
      "width": 6.4,
      "x": 47.14,
      "y": 8.04,
      "z": 0
    },
    "D6": {
      "depth": 85,
      "diameter": 6.4,
      "height": 85,
      "length": 6.4,
      "width": 6.4,
      "x": 56.14,
      "y": 8.04,
      "z": 0
    },
    "D7": {
      "depth": 85,
      "diameter": 6.4,
      "height": 85,
      "length": 6.4,
      "width": 6.4,
      "x": 65.14,
      "y": 8.04,
      "z": 0
    },
    "D8": {
      "depth": 85,
      "diameter": 6.4,
      "height": 85,
      "length": 6.4,
      "width": 6.4,
      "x": 74.14,
      "y": 8.04,
      "z": 0
    },
    "D9": {
      "depth": 85,
      "diameter": 6.4,
      "height": 85,
      "length": 6.4,
      "width": 6.4,
      "x": 83.14,
      "y": 8.04,
      "z": 0
    }
  }
}
